{
  "project_info": {
    "project_number": "226228762326",
    "firebase_url": "https://kaamkhoj-8f570.firebaseio.com",
    "project_id": "kaamkhoj-8f570",
    "storage_bucket": "kaamkhoj-8f570.appspot.com"
  },
  "client": [
    {
      "client_info": {
        "mobilesdk_app_id": "1:226228762326:android:6f849e70cb86080f42fb77",
        "android_client_info": {
          "package_name": "com.example.kaamkhoj"
        }
      },
      "oauth_client": [
        {
          "client_id": "226228762326-au7aenmcl0lgvr4r5f2ff72u8sdvv1k0.apps.googleusercontent.com",
          "client_type": 3
        }
      ],
      "api_key": [
        {
          "current_key": "AIzaSyDBaSGG4FIrSSe4QT-gCmCcC0YQUfS4K5M"
        }
      ],
      "services": {
        "appinvite_service": {
          "other_platform_oauth_client": [
            {
              "client_id": "226228762326-au7aenmcl0lgvr4r5f2ff72u8sdvv1k0.apps.googleusercontent.com",
              "client_type": 3
            }
          ]
        }
      }
    }
  ],
  "configuration_version": "1"
}